README.md
setup.py
datahub_metadata_sdk.egg-info/PKG-INFO
datahub_metadata_sdk.egg-info/SOURCES.txt
datahub_metadata_sdk.egg-info/dependency_links.txt
datahub_metadata_sdk.egg-info/entry_points.txt
datahub_metadata_sdk.egg-info/requires.txt
datahub_metadata_sdk.egg-info/top_level.txt
metadata/__init__.py
metadata/consts.py
metadata/context.py
metadata/ensure.py
metadata/exception.py
metadata/cli/__init__.py
metadata/cli/auth.py
metadata/cli/builtin/__init__.py
metadata/cli/builtin/dataset.py
metadata/cli/builtin/dataset_group.py
metadata/cli/builtin/entity.py
metadata/cli/builtin/model.py
metadata/cli/builtin/model_group.py
metadata/cli/commands/__init__.py
metadata/cli/commands/context.py
metadata/cli/commands/login.py
metadata/cli/commands/metadata.py
metadata/cli/scripts/__init__.py
metadata/cli/scripts/serve.py
metadata/client/__init__.py
metadata/client/client.py
metadata/client/mixins/__init__.py
metadata/client/mixins/dataset.py
metadata/client/mixins/dataset_group.py
metadata/client/mixins/model.py
metadata/client/mixins/model_group.py
metadata/client/mixins/task.py
metadata/client/mixins/workflow.py
metadata/client/resources/queries/browse.graphql
metadata/client/resources/queries/container.graphql
metadata/client/resources/queries/container.relationships.graphql
metadata/client/resources/queries/dataset.graphql
metadata/client/resources/queries/entityExists.graphql
metadata/client/resources/queries/me.graphql
metadata/client/resources/queries/mlModel.graphql
metadata/client/resources/queries/mlModelGroup.graphql
metadata/client/resources/queries/mlModelGroup.relationships.graphql
metadata/client/resources/queries/searchAcrossEntities.graphql
metadata/client/resources/queries/searchAcrossLineage.graphql
metadata/entity/__init__.py
metadata/entity/dataset.py
metadata/entity/dataset_group.py
metadata/entity/entity.py
metadata/entity/model.py
metadata/entity/model_group.py
metadata/entity/task.py
metadata/entity/workflow.py
metadata/utils/__init__.py
metadata/utils/edit.py
metadata/utils/format.py
metadata/utils/ipython.py
metadata/utils/lang.py
metadata/utils/page.py
metadata/utils/storage.py
metadata/utils/time.py
metadata/utils/url.py