Metadata-Version: 2.1
Name: datahub-metadata-sdk
Version: 0.0.20
Summary: Datahub metastore concept Simplified.
Author: DP Technology
Requires-Python: >=3.8
Provides-Extra: cli
